{
    "version": "4.13.5",
    "description": "An Electron-based unofficial desktop client for ProtonMail.",
    "homepage": "https://github.com/vladimiry/ElectronMail",
    "license": "MIT",
    "url": "https://github.com/vladimiry/ElectronMail/releases/download/v4.13.5/electron-mail-4.13.5-windows-x64-nsis-installer.exe#/dl.7z",
    "hash": "3f4294cfe13722c9285d1a98863cf1a79c0b4373077f16385db5c060ea43512e",
    "installer": {
        "script": "Expand-7zipArchive \"$dir\\`$PLUGINSDIR\\app-64.7z\" -Removal"
    },
    "bin": "$PLUGINSDIR/ElectronMail.exe",
    "shortcuts": [
        [
            "$PLUGINSDIR/ElectronMail.exe",
            "ElectronMail"
        ]
    ],
    "checkver": "github",
    "autoupdate": {
        "url": "https://github.com/vladimiry/ElectronMail/releases/download/v$version/electron-mail-$version-windows-x64-nsis-installer.exe#/dl.7z",
        "hash": "$url.sha256"
    }
}
